curseradio_improved/__init__.py
curseradio_improved/__main__.py
curseradio_improved/configs.json
curseradio_improved/curseradio_improved.py
curseradio_improved-0.3.8.dist-info/LICENSE.md
curseradio_improved-0.3.8.dist-info/METADATA
curseradio_improved-0.3.8.dist-info/WHEEL
curseradio_improved-0.3.8.dist-info/entry_points.txt
curseradio_improved-0.3.8.dist-info/top_level.txt
curseradio_improved-0.3.8.dist-info/RECORD
