Metadata-Version: 2.1
Name: curseradio-improved
Version: 0.3.8
Summary: An improved Curses interface for listening to internet radio.
Home-page: https://github.com/DanielSchuette/curseradio-improved
Author: Daniel Schuette
Author-email: d.schuette@online.de
License: MIT
Platform: UNKNOWN
Classifier: Development Status :: 3 - Alpha
Classifier: License :: OSI Approved :: MIT License
Classifier: Programming Language :: Python :: 3.7
Requires: lxml
Requires: requests
Requires: pyxdg
Requires-Python: >=3.7
